update_plex.py
update_plex-1.3.0.dist-info/DESCRIPTION.rst
update_plex-1.3.0.dist-info/METADATA
update_plex-1.3.0.dist-info/RECORD
update_plex-1.3.0.dist-info/WHEEL
update_plex-1.3.0.dist-info/entry_points.txt
update_plex-1.3.0.dist-info/metadata.json
update_plex-1.3.0.dist-info/top_level.txt
