Metadata-Version: 2.0
Name: update-plex
Version: 1.3.0
Summary: Tell your Plex TV library to update
Home-page: https://github.com/ghickman/update_plex
Author: George Hickman
Author-email: george@ghickman.co.uk
License: MIT
Platform: UNKNOWN
Requires-Dist: click
Requires-Dist: requests
